LICENSE.txt
README.md
setup.cfg
setup.py
claritygov/__init__.py
claritygov/api_config.py
claritygov/utils.py
claritygov.egg-info/PKG-INFO
claritygov.egg-info/SOURCES.txt
claritygov.egg-info/dependency_links.txt
claritygov.egg-info/requires.txt
claritygov.egg-info/top_level.txt
claritygov/models/Bill.py
claritygov/models/Committee.py
claritygov/models/CommitteeVote.py
claritygov/models/Delegate.py
claritygov/models/HTTPValidationError.py
claritygov/models/Member.py
claritygov/models/Message.py
claritygov/models/Party.py
claritygov/models/Senator.py
claritygov/models/ValidationError.py
claritygov/models/__init__.py
claritygov/services/__init__.py
claritygov/services/bills_service.py
claritygov/services/committees_service.py
claritygov/services/legislators_service.py
claritygov/services/root_service.py
claritygov/services/votes_service.py