Metadata-Version: 2.1
Name: claritygov
Version: 0.2.1
Summary: Python API Client for ClarityGov, a free public developer API for accessing government legislative data in a standardized format.
Download-URL: https://github.com/ianmcvann/ClarityGovClient/archive/refs/tags/v0.1.0.tar.gz
Author: ClarityGov
License: Creative Commons Attribution 4.0 International Public License
Keywords: claritygov,clarityapi,government,transparency
Classifier: Development Status :: 3 - Alpha
Classifier: Intended Audience :: Developers
Classifier: Programming Language :: Python :: 3.7
Classifier: Programming Language :: Python :: 3.8
Classifier: Programming Language :: Python :: 3.9
Classifier: Programming Language :: Python :: 3
License-File: LICENSE.txt
